pykitables/__init__.py
pykitables/wikirow.py
pykitables/wikitable.py
pykitables-0.0.2.dist-info/LICENSE
pykitables-0.0.2.dist-info/METADATA
pykitables-0.0.2.dist-info/WHEEL
pykitables-0.0.2.dist-info/top_level.txt
pykitables-0.0.2.dist-info/RECORD
