Metadata-Version: 2.1
Name: pykitables
Version: 0.0.2
Summary: Get neatly formatted tables from any Wikipedia article
Home-page: https://github.com/omshii/pykitables
Author: Omshi Samal
Author-email: omshisamal72@gmail.com
License: UNKNOWN
Platform: UNKNOWN
Classifier: Programming Language :: Python :: 3
Classifier: License :: OSI Approved :: MIT License
Classifier: Operating System :: OS Independent
Requires-Python: >=3.6
Requires-Dist: beautifulsoup4
Requires-Dist: requests
